{
  "repos": [
    [
      "caarlos0/domain_exporter",
      [
        {
          "url": "https://github.com/caarlos0/domain_exporter/pull/87",
          "title": "feat: add .jp domain support",
          "label": "caarlos0/domain_exporter#87",
          "repoUser": "caarlos0",
          "repoName": "domain_exporter",
          "prId": 87
        }
      ]
    ],
    [
      "antfu/vite-ssg",
      [
        {
          "url": "https://github.com/antfu/vite-ssg/pull/14",
          "title": "fix: config was not applied",
          "label": "antfu/vite-ssg#14",
          "repoUser": "antfu",
          "repoName": "vite-ssg",
          "prId": 14
        }
      ]
    ],
    [
      "microsoft/vscode-html-languageservice",
      [
        {
          "url": "https://github.com/microsoft/vscode-html-languageservice/pull/99",
          "title": "Remove existing attribute from autocomplete suggestions",
          "label": "microsoft/vscode-html-languageservice#99",
          "repoUser": "microsoft",
          "repoName": "vscode-html-languageservice",
          "prId": 99
        }
      ]
    ],
    [
      "OpenAPITools/openapi-generator",
      [
        {
          "url": "https://github.com/OpenAPITools/openapi-generator/pull/8283",
          "title": "[typescript-axios] reduce file size",
          "label": "OpenAPITools/openapi-generator#8283",
          "repoUser": "OpenAPITools",
          "repoName": "openapi-generator",
          "prId": 8283
        },
        {
          "url": "https://github.com/OpenAPITools/openapi-generator/pull/7477",
          "title": "[typescript-axios] support \"x-enum-descriptions\"",
          "label": "OpenAPITools/openapi-generator#7477",
          "repoUser": "OpenAPITools",
          "repoName": "openapi-generator",
          "prId": 7477
        },
        {
          "url": "https://github.com/OpenAPITools/openapi-generator/pull/7476",
          "title": "[typescript-axios] replace optional-chaining",
          "label": "OpenAPITools/openapi-generator#7476",
          "repoUser": "OpenAPITools",
          "repoName": "openapi-generator",
          "prId": 7476
        },
        {
          "url": "https://github.com/OpenAPITools/openapi-generator/pull/7475",
          "title": "[typescript-axios] rename query parameters to avoid collision",
          "label": "OpenAPITools/openapi-generator#7475",
          "repoUser": "OpenAPITools",
          "repoName": "openapi-generator",
          "prId": 7475
        },
        {
          "url": "https://github.com/OpenAPITools/openapi-generator/pull/6960",
          "title": "[typescript-axios] switched to new URL API",
          "label": "OpenAPITools/openapi-generator#6960",
          "repoUser": "OpenAPITools",
          "repoName": "openapi-generator",
          "prId": 6960
        }
      ]
    ],
    [
      "marcello3d/node-tosource",
      [
        {
          "url": "https://github.com/marcello3d/node-tosource/pull/31",
          "title": "fix typings field",
          "label": "marcello3d/node-tosource#31",
          "repoUser": "marcello3d",
          "repoName": "node-tosource",
          "prId": 31
        }
      ]
    ],
    [
      "vuejs/eslint-plugin-vue",
      [
        {
          "url": "https://github.com/vuejs/eslint-plugin-vue/pull/1407",
          "title": "Add composition api's computed function support to vue/no-side-effects-in-computed-properties close #1393",
          "label": "vuejs/eslint-plugin-vue#1407",
          "repoUser": "vuejs",
          "repoName": "eslint-plugin-vue",
          "prId": 1407
        },
        {
          "url": "https://github.com/vuejs/eslint-plugin-vue/pull/1406",
          "title": "Add composition api's computed function support to vue/return-in-computed-property refs #1393",
          "label": "vuejs/eslint-plugin-vue#1406",
          "repoUser": "vuejs",
          "repoName": "eslint-plugin-vue",
          "prId": 1406
        },
        {
          "url": "https://github.com/vuejs/eslint-plugin-vue/pull/1398",
          "title": "Add composition api's computed function support to vue/no-async-in-computed-properties refs #1393",
          "label": "vuejs/eslint-plugin-vue#1398",
          "repoUser": "vuejs",
          "repoName": "eslint-plugin-vue",
          "prId": 1398
        },
        {
          "url": "https://github.com/vuejs/eslint-plugin-vue/pull/1396",
          "title": "Make no-ref-as-operand fixable close #1394",
          "label": "vuejs/eslint-plugin-vue#1396",
          "repoUser": "vuejs",
          "repoName": "eslint-plugin-vue",
          "prId": 1396
        }
      ]
    ],
    [
      "vuejs/vetur",
      [
        {
          "url": "https://github.com/vuejs/vetur/pull/2565",
          "title": "Dont include used attributes in suggestions",
          "label": "vuejs/vetur#2565",
          "repoUser": "vuejs",
          "repoName": "vetur",
          "prId": 2565
        },
        {
          "url": "https://github.com/vuejs/vetur/pull/2558",
          "title": "Custom event auto complete",
          "label": "vuejs/vetur#2558",
          "repoUser": "vuejs",
          "repoName": "vetur",
          "prId": 2558
        },
        {
          "url": "https://github.com/vuejs/vetur/pull/2557",
          "title": "sort attribute suggestion without `:` or `@`",
          "label": "vuejs/vetur#2557",
          "repoUser": "vuejs",
          "repoName": "vetur",
          "prId": 2557
        },
        {
          "url": "https://github.com/vuejs/vetur/pull/2214",
          "title": "Add line break in JSDoc",
          "label": "vuejs/vetur#2214",
          "repoUser": "vuejs",
          "repoName": "vetur",
          "prId": 2214
        }
      ]
    ],
    [
      "vueuse/vue-chemistry",
      [
        {
          "url": "https://github.com/vueuse/vue-chemistry/pull/5",
          "title": "refactor!: rename all to index and index to core",
          "label": "vueuse/vue-chemistry#5",
          "repoUser": "vueuse",
          "repoName": "vue-chemistry",
          "prId": 5
        }
      ]
    ],
    [
      "antfu/purge-icons",
      [
        {
          "url": "https://github.com/antfu/purge-icons/pull/12",
          "title": "fix: add exports field in package.json",
          "label": "antfu/purge-icons#12",
          "repoUser": "antfu",
          "repoName": "purge-icons",
          "prId": 12
        }
      ]
    ],
    [
      "antfu/vue-chemistry",
      [
        {
          "url": "https://github.com/antfu/vue-chemistry/pull/2",
          "title": "fix not able to import with 'vue-chemistry'",
          "label": "antfu/vue-chemistry#2",
          "repoUser": "antfu",
          "repoName": "vue-chemistry",
          "prId": 2
        }
      ]
    ],
    [
      "eslint/eslint-release",
      [
        {
          "url": "https://github.com/eslint/eslint-release/pull/48",
          "title": "Fix: env var names are case-insensitive in windows",
          "label": "eslint/eslint-release#48",
          "repoUser": "eslint",
          "repoName": "eslint-release",
          "prId": 48
        },
        {
          "url": "https://github.com/eslint/eslint-release/pull/47",
          "title": "Update: group commits by types in release log (fixes #46)",
          "label": "eslint/eslint-release#47",
          "repoUser": "eslint",
          "repoName": "eslint-release",
          "prId": 47
        }
      ]
    ],
    [
      "vitejs/vite",
      [
        {
          "url": "https://github.com/vitejs/vite/pull/620",
          "title": "fix(dev): replace config.define instead of inserting object",
          "label": "vitejs/vite#620",
          "repoUser": "vitejs",
          "repoName": "vite",
          "prId": 620
        }
      ]
    ],
    [
      "vuejs/composition-api",
      [
        {
          "url": "https://github.com/vuejs/composition-api/pull/446",
          "title": "fix PropType",
          "label": "vuejs/composition-api#446",
          "repoUser": "vuejs",
          "repoName": "composition-api",
          "prId": 446
        },
        {
          "url": "https://github.com/vuejs/composition-api/pull/371",
          "title": "reapply #352 and fix test: Remove Function type from PropType type",
          "label": "vuejs/composition-api#371",
          "repoUser": "vuejs",
          "repoName": "composition-api",
          "prId": 371
        }
      ]
    ],
    [
      "protobufjs/protobuf.js",
      [
        {
          "url": "https://github.com/protobufjs/protobuf.js/pull/1446",
          "title": "fix: es6 export enum",
          "label": "protobufjs/protobuf.js#1446",
          "repoUser": "protobufjs",
          "repoName": "protobuf.js",
          "prId": 1446
        }
      ]
    ],
    [
      "paroi-tech/direct-vuex",
      [
        {
          "url": "https://github.com/paroi-tech/direct-vuex/pull/53",
          "title": "Changed state and getters to readonly",
          "label": "paroi-tech/direct-vuex#53",
          "repoUser": "paroi-tech",
          "repoName": "direct-vuex",
          "prId": 53
        }
      ]
    ],
    [
      "tensorflow/tfjs",
      [
        {
          "url": "https://github.com/tensorflow/tfjs/pull/2543",
          "title": "[WASM] Add Greater, GreaterEqual kernels",
          "label": "tensorflow/tfjs#2543",
          "repoUser": "tensorflow",
          "repoName": "tfjs",
          "prId": 2543
        },
        {
          "url": "https://github.com/tensorflow/tfjs/pull/2528",
          "title": "[wasm] Add Minimum, Maximum kernels",
          "label": "tensorflow/tfjs#2528",
          "repoUser": "tensorflow",
          "repoName": "tfjs",
          "prId": 2528
        }
      ]
    ],
    [
      "DefinitelyTyped/DefinitelyTyped",
      [
        {
          "url": "https://github.com/DefinitelyTyped/DefinitelyTyped/pull/40647",
          "title": "Update KaTeX to v0.11.1",
          "label": "DefinitelyTyped/DefinitelyTyped#40647",
          "repoUser": "DefinitelyTyped",
          "repoName": "DefinitelyTyped",
          "prId": 40647
        }
      ]
    ]
  ],
  "fetchedAt": "2021-03-15T11:19:41.020Z"
}